.gitignore
LICENSE.txt
README.md
requirements.txt
setup.cfg
setup.py
Image_Preprocessing_Optimization/CustomFunctions.py
Image_Preprocessing_Optimization/ImageGridSearch.py
Image_Preprocessing_Optimization/image_src/b_1.jpg
Image_Preprocessing_Optimization/image_src/b_10.jpg
Image_Preprocessing_Optimization/image_src/b_2.jpg
Image_Preprocessing_Optimization/image_src/b_3.jpg
Image_Preprocessing_Optimization/image_src/b_4.jpg
Image_Preprocessing_Optimization/image_src/b_5.jpg
Image_Preprocessing_Optimization/image_src/b_6.jpg
Image_Preprocessing_Optimization/image_src/b_7.jpg
Image_Preprocessing_Optimization/image_src/b_8.jpg
Image_Preprocessing_Optimization/image_src/b_9.jpg
Image_Preprocessing_Optimization/image_src/sentence_eight.jpg
Image_Preprocessing_Optimization/image_src/sentence_five.jpg
Image_Preprocessing_Optimization/image_src/sentence_four.jpg
Image_Preprocessing_Optimization/image_src/sentence_nine.jpg
Image_Preprocessing_Optimization/image_src/sentence_one.jpg
Image_Preprocessing_Optimization/image_src/sentence_seven.jpg
Image_Preprocessing_Optimization/image_src/sentence_six.jpg
Image_Preprocessing_Optimization/image_src/sentence_ten.jpg
Image_Preprocessing_Optimization/image_src/sentence_three.jpg
Image_Preprocessing_Optimization/image_src/sentence_two.jpg
Image_Preprocessing_Optimization/text_src/b_1.txt
Image_Preprocessing_Optimization/text_src/b_10.txt
Image_Preprocessing_Optimization/text_src/b_2.txt
Image_Preprocessing_Optimization/text_src/b_3.txt
Image_Preprocessing_Optimization/text_src/b_4.txt
Image_Preprocessing_Optimization/text_src/b_5.txt
Image_Preprocessing_Optimization/text_src/b_6.txt
Image_Preprocessing_Optimization/text_src/b_7.txt
Image_Preprocessing_Optimization/text_src/b_8.txt
Image_Preprocessing_Optimization/text_src/b_9.txt
Image_Preprocessing_Optimization/text_src/sentence_eight.txt
Image_Preprocessing_Optimization/text_src/sentence_five.txt
Image_Preprocessing_Optimization/text_src/sentence_four.txt
StudiOCR.egg-info/PKG-INFO
StudiOCR.egg-info/SOURCES.txt
StudiOCR.egg-info/dependency_links.txt
StudiOCR.egg-info/entry_points.txt
StudiOCR.egg-info/requires.txt
StudiOCR.egg-info/top_level.txt
